queue_bqsr_status
