Metadata-Version: 1.1
Name: queue-bqsr-status
Version: 0.8
Summary: write bqsr db status
Home-page: https://github.com/NCI-GDC/queue_bqsr_status
Author: Jeremiah H. Savage
Author-email: jeremiahsavage@gmail.com
License: Apache 2.0
Platform: UNKNOWN
Classifier: Development Status :: 3 - Alpha
Classifier: Intended Audience :: Developers
Classifier: License :: OSI Approved :: Apache Software License
Classifier: Programming Language :: Python
Classifier: Programming Language :: Python :: 3
